{
    "os": "Linux-5.4.0-52-generic-x86_64-with-glibc2.29",
    "python": "3.8.10",
    "heartbeatAt": "2023-05-26T21:51:41.177493",
    "startedAt": "2023-05-26T21:51:40.149946",
    "docker": null,
    "cuda": null,
    "args": [
        "-n_gpu",
        "1",
        "-save_dir",
        "/workdir/results/26_05_2023",
        "-ddir",
        "/workdir/sf_pv",
        "-afile",
        "annotations_file_short_SF.csv",
        "-library",
        "timm",
        "-model_name",
        "resnet34",
        "-pretrain_w",
        "0",
        "-emb_size",
        "256",
        "-n_b",
        "200",
        "-n_w",
        "100",
        "-b_s",
        "64",
        "-modality",
        "wav",
        "-n_epochs",
        "100",
        "-fine_tune",
        "1",
        "-n_fft",
        "1024",
        "-hop_length",
        "512",
        "-n_mels",
        "128",
        "-sample_duration",
        "3",
        "-exp_name",
        "exp6_n_ways_100_n_support_5",
        "-pool",
        "SAP",
        "-n_s",
        "5",
        "-weight_decay",
        "0.01"
    ],
    "state": "running",
    "program": "issai_task_3_train.py",
    "codePath": "issai_task_3_train.py",
    "git": {
        "remote": "https://github.com/Allessyer/Speaker-Verification.git",
        "commit": "2495880ca3e521cb245b0440dde34edda2b60108"
    },
    "email": null,
    "root": "/workdir/github",
    "host": "a96f70e4c266",
    "username": "root",
    "executable": "/usr/bin/python",
    "cpu_count": 128,
    "cpu_count_logical": 256,
    "cpu_freq": {
        "current": 2883.867640625001,
        "min": 1500.0,
        "max": 2250.0
    },
    "cpu_freq_per_core": [
        {
            "current": 3384.49,
            "min": 1500.0,
            "max": 2250.0
        },
        {
            "current": 2924.305,
            "min": 1500.0,
            "max": 2250.0
        },
        {
            "current": 3143.739,
            "min": 1500.0,
            "max": 2250.0
        },
        {
            "current": 3128.401,
            "min": 1500.0,
            "max": 2250.0
        },
        {
            "current": 3391.642,
            "min": 1500.0,
            "max": 2250.0
        },
        {
            "current": 2204.641,
            "min": 1500.0,
            "max": 2250.0
        },
        {
            "current": 2200.105,
            "min": 1500.0,
            "max": 2250.0
        },
        {
            "current": 2201.35,
            "min": 1500.0,
            "max": 2250.0
        },
        {
            "current": 3089.22,
            "min": 1500.0,
            "max": 2250.0
        },
        {
            "current": 3387.71,
            "min": 1500.0,
            "max": 2250.0
        },
        {
            "current": 3379.13,
            "min": 1500.0,
            "max": 2250.0
        },
        {
            "current": 3398.87,
            "min": 1500.0,
            "max": 2250.0
        },
        {
            "current": 3378.077,
            "min": 1500.0,
            "max": 2250.0
        },
        {
            "current": 3385.636,
            "min": 1500.0,
            "max": 2250.0
        },
        {
            "current": 3398.156,
            "min": 1500.0,
            "max": 2250.0
        },
        {
            "current": 3110.874,
            "min": 1500.0,
            "max": 2250.0
        },
        {
            "current": 3389.811,
            "min": 1500.0,
            "max": 2250.0
        },
        {
            "current": 2616.624,
            "min": 1500.0,
            "max": 2250.0
        },
        {
            "current": 3394.615,
            "min": 1500.0,
            "max": 2250.0
        },
        {
            "current": 2228.062,
            "min": 1500.0,
            "max": 2250.0
        },
        {
            "current": 3191.942,
            "min": 1500.0,
            "max": 2250.0
        },
        {
            "current": 2219.713,
            "min": 1500.0,
            "max": 2250.0
        },
        {
            "current": 3386.386,
            "min": 1500.0,
            "max": 2250.0
        },
        {
            "current": 2465.598,
            "min": 1500.0,
            "max": 2250.0
        },
        {
            "current": 3382.975,
            "min": 1500.0,
            "max": 2250.0
        },
        {
            "current": 3393.888,
            "min": 1500.0,
            "max": 2250.0
        },
        {
            "current": 3393.299,
            "min": 1500.0,
            "max": 2250.0
        },
        {
            "current": 3400.769,
            "min": 1500.0,
            "max": 2250.0
        },
        {
            "current": 3381.268,
            "min": 1500.0,
            "max": 2250.0
        },
        {
            "current": 3399.132,
            "min": 1500.0,
            "max": 2250.0
        },
        {
            "current": 3407.298,
            "min": 1500.0,
            "max": 2250.0
        },
        {
            "current": 3373.009,
            "min": 1500.0,
            "max": 2250.0
        },
        {
            "current": 3393.94,
            "min": 1500.0,
            "max": 2250.0
        },
        {
            "current": 3376.388,
            "min": 1500.0,
            "max": 2250.0
        },
        {
            "current": 3388.4,
            "min": 1500.0,
            "max": 2250.0
        },
        {
            "current": 3394.445,
            "min": 1500.0,
            "max": 2250.0
        },
        {
            "current": 3389.059,
            "min": 1500.0,
            "max": 2250.0
        },
        {
            "current": 3388.29,
            "min": 1500.0,
            "max": 2250.0
        },
        {
            "current": 3388.928,
            "min": 1500.0,
            "max": 2250.0
        },
        {
            "current": 3393.888,
            "min": 1500.0,
            "max": 2250.0
        },
        {
            "current": 3385.399,
            "min": 1500.0,
            "max": 2250.0
        },
        {
            "current": 3376.915,
            "min": 1500.0,
            "max": 2250.0
        },
        {
            "current": 3374.666,
            "min": 1500.0,
            "max": 2250.0
        },
        {
            "current": 3378.602,
            "min": 1500.0,
            "max": 2250.0
        },
        {
            "current": 3390.871,
            "min": 1500.0,
            "max": 2250.0
        },
        {
            "current": 3384.988,
            "min": 1500.0,
            "max": 2250.0
        },
        {
            "current": 3382.265,
            "min": 1500.0,
            "max": 2250.0
        },
        {
            "current": 3393.824,
            "min": 1500.0,
            "max": 2250.0
        },
        {
            "current": 3378.041,
            "min": 1500.0,
            "max": 2250.0
        },
        {
            "current": 3393.007,
            "min": 1500.0,
            "max": 2250.0
        },
        {
            "current": 3397.034,
            "min": 1500.0,
            "max": 2250.0
        },
        {
            "current": 3396.397,
            "min": 1500.0,
            "max": 2250.0
        },
        {
            "current": 3393.931,
            "min": 1500.0,
            "max": 2250.0
        },
        {
            "current": 3385.957,
            "min": 1500.0,
            "max": 2250.0
        },
        {
            "current": 3392.263,
            "min": 1500.0,
            "max": 2250.0
        },
        {
            "current": 3381.123,
            "min": 1500.0,
            "max": 2250.0
        },
        {
            "current": 3396.783,
            "min": 1500.0,
            "max": 2250.0
        },
        {
            "current": 3386.211,
            "min": 1500.0,
            "max": 2250.0
        },
        {
            "current": 3391.394,
            "min": 1500.0,
            "max": 2250.0
        },
        {
            "current": 3378.635,
            "min": 1500.0,
            "max": 2250.0
        },
        {
            "current": 3387.687,
            "min": 1500.0,
            "max": 2250.0
        },
        {
            "current": 3392.962,
            "min": 1500.0,
            "max": 2250.0
        },
        {
            "current": 3379.034,
            "min": 1500.0,
            "max": 2250.0
        },
        {
            "current": 3393.155,
            "min": 1500.0,
            "max": 2250.0
        },
        {
            "current": 2161.411,
            "min": 1500.0,
            "max": 2250.0
        },
        {
            "current": 3383.24,
            "min": 1500.0,
            "max": 2250.0
        },
        {
            "current": 3380.668,
            "min": 1500.0,
            "max": 2250.0
        },
        {
            "current": 2579.091,
            "min": 1500.0,
            "max": 2250.0
        },
        {
            "current": 3386.577,
            "min": 1500.0,
            "max": 2250.0
        },
        {
            "current": 3385.691,
            "min": 1500.0,
            "max": 2250.0
        },
        {
            "current": 3390.13,
            "min": 1500.0,
            "max": 2250.0
        },
        {
            "current": 3382.342,
            "min": 1500.0,
            "max": 2250.0
        },
        {
            "current": 3381.936,
            "min": 1500.0,
            "max": 2250.0
        },
        {
            "current": 2592.268,
            "min": 1500.0,
            "max": 2250.0
        },
        {
            "current": 2596.529,
            "min": 1500.0,
            "max": 2250.0
        },
        {
            "current": 2577.033,
            "min": 1500.0,
            "max": 2250.0
        },
        {
            "current": 3389.852,
            "min": 1500.0,
            "max": 2250.0
        },
        {
            "current": 3380.431,
            "min": 1500.0,
            "max": 2250.0
        },
        {
            "current": 3365.58,
            "min": 1500.0,
            "max": 2250.0
        },
        {
            "current": 3395.033,
            "min": 1500.0,
            "max": 2250.0
        },
        {
            "current": 3388.252,
            "min": 1500.0,
            "max": 2250.0
        },
        {
            "current": 3391.024,
            "min": 1500.0,
            "max": 2250.0
        },
        {
            "current": 3390.276,
            "min": 1500.0,
            "max": 2250.0
        },
        {
            "current": 3378.681,
            "min": 1500.0,
            "max": 2250.0
        },
        {
            "current": 3387.901,
            "min": 1500.0,
            "max": 2250.0
        },
        {
            "current": 3391.424,
            "min": 1500.0,
            "max": 2250.0
        },
        {
            "current": 3388.365,
            "min": 1500.0,
            "max": 2250.0
        },
        {
            "current": 2524.402,
            "min": 1500.0,
            "max": 2250.0
        },
        {
            "current": 2483.671,
            "min": 1500.0,
            "max": 2250.0
        },
        {
            "current": 3390.032,
            "min": 1500.0,
            "max": 2250.0
        },
        {
            "current": 2525.392,
            "min": 1500.0,
            "max": 2250.0
        },
        {
            "current": 3375.162,
            "min": 1500.0,
            "max": 2250.0
        },
        {
            "current": 3404.983,
            "min": 1500.0,
            "max": 2250.0
        },
        {
            "current": 3388.901,
            "min": 1500.0,
            "max": 2250.0
        },
        {
            "current": 3376.221,
            "min": 1500.0,
            "max": 2250.0
        },
        {
            "current": 3389.66,
            "min": 1500.0,
            "max": 2250.0
        },
        {
            "current": 3381.18,
            "min": 1500.0,
            "max": 2250.0
        },
        {
            "current": 3382.233,
            "min": 1500.0,
            "max": 2250.0
        },
        {
            "current": 3392.349,
            "min": 1500.0,
            "max": 2250.0
        },
        {
            "current": 3394.221,
            "min": 1500.0,
            "max": 2250.0
        },
        {
            "current": 3392.047,
            "min": 1500.0,
            "max": 2250.0
        },
        {
            "current": 3381.433,
            "min": 1500.0,
            "max": 2250.0
        },
        {
            "current": 3381.31,
            "min": 1500.0,
            "max": 2250.0
        },
        {
            "current": 3379.554,
            "min": 1500.0,
            "max": 2250.0
        },
        {
            "current": 2467.811,
            "min": 1500.0,
            "max": 2250.0
        },
        {
            "current": 2521.724,
            "min": 1500.0,
            "max": 2250.0
        },
        {
            "current": 3384.224,
            "min": 1500.0,
            "max": 2250.0
        },
        {
            "current": 2503.779,
            "min": 1500.0,
            "max": 2250.0
        },
        {
            "current": 3382.657,
            "min": 1500.0,
            "max": 2250.0
        },
        {
            "current": 3390.797,
            "min": 1500.0,
            "max": 2250.0
        },
        {
            "current": 2390.859,
            "min": 1500.0,
            "max": 2250.0
        },
        {
            "current": 3392.941,
            "min": 1500.0,
            "max": 2250.0
        },
        {
            "current": 3383.647,
            "min": 1500.0,
            "max": 2250.0
        },
        {
            "current": 3385.95,
            "min": 1500.0,
            "max": 2250.0
        },
        {
            "current": 3230.296,
            "min": 1500.0,
            "max": 2250.0
        },
        {
            "current": 3387.467,
            "min": 1500.0,
            "max": 2250.0
        },
        {
            "current": 2356.426,
            "min": 1500.0,
            "max": 2250.0
        },
        {
            "current": 3288.63,
            "min": 1500.0,
            "max": 2250.0
        },
        {
            "current": 2378.489,
            "min": 1500.0,
            "max": 2250.0
        },
        {
            "current": 3389.078,
            "min": 1500.0,
            "max": 2250.0
        },
        {
            "current": 3388.374,
            "min": 1500.0,
            "max": 2250.0
        },
        {
            "current": 3395.361,
            "min": 1500.0,
            "max": 2250.0
        },
        {
            "current": 2523.11,
            "min": 1500.0,
            "max": 2250.0
        },
        {
            "current": 2484.085,
            "min": 1500.0,
            "max": 2250.0
        },
        {
            "current": 3389.247,
            "min": 1500.0,
            "max": 2250.0
        },
        {
            "current": 3383.117,
            "min": 1500.0,
            "max": 2250.0
        },
        {
            "current": 3391.915,
            "min": 1500.0,
            "max": 2250.0
        },
        {
            "current": 3379.148,
            "min": 1500.0,
            "max": 2250.0
        },
        {
            "current": 3395.959,
            "min": 1500.0,
            "max": 2250.0
        },
        {
            "current": 2176.237,
            "min": 1500.0,
            "max": 2250.0
        },
        {
            "current": 3387.65,
            "min": 1500.0,
            "max": 2250.0
        },
        {
            "current": 3395.315,
            "min": 1500.0,
            "max": 2250.0
        },
        {
            "current": 3383.672,
            "min": 1500.0,
            "max": 2250.0
        },
        {
            "current": 2200.313,
            "min": 1500.0,
            "max": 2250.0
        },
        {
            "current": 2197.895,
            "min": 1500.0,
            "max": 2250.0
        },
        {
            "current": 2188.967,
            "min": 1500.0,
            "max": 2250.0
        },
        {
            "current": 3399.994,
            "min": 1500.0,
            "max": 2250.0
        },
        {
            "current": 3382.058,
            "min": 1500.0,
            "max": 2250.0
        },
        {
            "current": 3407.977,
            "min": 1500.0,
            "max": 2250.0
        },
        {
            "current": 3385.505,
            "min": 1500.0,
            "max": 2250.0
        },
        {
            "current": 3385.344,
            "min": 1500.0,
            "max": 2250.0
        },
        {
            "current": 3388.456,
            "min": 1500.0,
            "max": 2250.0
        },
        {
            "current": 3389.932,
            "min": 1500.0,
            "max": 2250.0
        },
        {
            "current": 3376.192,
            "min": 1500.0,
            "max": 2250.0
        },
        {
            "current": 3392.893,
            "min": 1500.0,
            "max": 2250.0
        },
        {
            "current": 2692.579,
            "min": 1500.0,
            "max": 2250.0
        },
        {
            "current": 3382.699,
            "min": 1500.0,
            "max": 2250.0
        },
        {
            "current": 2194.188,
            "min": 1500.0,
            "max": 2250.0
        },
        {
            "current": 3388.737,
            "min": 1500.0,
            "max": 2250.0
        },
        {
            "current": 2198.86,
            "min": 1500.0,
            "max": 2250.0
        },
        {
            "current": 3396.832,
            "min": 1500.0,
            "max": 2250.0
        },
        {
            "current": 2627.994,
            "min": 1500.0,
            "max": 2250.0
        },
        {
            "current": 2260.984,
            "min": 1500.0,
            "max": 2250.0
        },
        {
            "current": 3391.942,
            "min": 1500.0,
            "max": 2250.0
        },
        {
            "current": 3385.181,
            "min": 1500.0,
            "max": 2250.0
        },
        {
            "current": 3371.924,
            "min": 1500.0,
            "max": 2250.0
        },
        {
            "current": 3385.274,
            "min": 1500.0,
            "max": 2250.0
        },
        {
            "current": 3378.528,
            "min": 1500.0,
            "max": 2250.0
        },
        {
            "current": 3378.271,
            "min": 1500.0,
            "max": 2250.0
        },
        {
            "current": 3379.255,
            "min": 1500.0,
            "max": 2250.0
        },
        {
            "current": 3393.242,
            "min": 1500.0,
            "max": 2250.0
        },
        {
            "current": 3400.032,
            "min": 1500.0,
            "max": 2250.0
        },
        {
            "current": 3381.309,
            "min": 1500.0,
            "max": 2250.0
        },
        {
            "current": 3378.498,
            "min": 1500.0,
            "max": 2250.0
        },
        {
            "current": 3391.083,
            "min": 1500.0,
            "max": 2250.0
        },
        {
            "current": 3393.337,
            "min": 1500.0,
            "max": 2250.0
        },
        {
            "current": 3392.108,
            "min": 1500.0,
            "max": 2250.0
        },
        {
            "current": 3380.812,
            "min": 1500.0,
            "max": 2250.0
        },
        {
            "current": 3390.679,
            "min": 1500.0,
            "max": 2250.0
        },
        {
            "current": 3397.14,
            "min": 1500.0,
            "max": 2250.0
        },
        {
            "current": 3384.8,
            "min": 1500.0,
            "max": 2250.0
        },
        {
            "current": 3387.812,
            "min": 1500.0,
            "max": 2250.0
        },
        {
            "current": 3374.745,
            "min": 1500.0,
            "max": 2250.0
        },
        {
            "current": 3389.461,
            "min": 1500.0,
            "max": 2250.0
        },
        {
            "current": 3379.284,
            "min": 1500.0,
            "max": 2250.0
        },
        {
            "current": 3379.183,
            "min": 1500.0,
            "max": 2250.0
        },
        {
            "current": 3394.862,
            "min": 1500.0,
            "max": 2250.0
        },
        {
            "current": 3384.983,
            "min": 1500.0,
            "max": 2250.0
        },
        {
            "current": 3408.027,
            "min": 1500.0,
            "max": 2250.0
        },
        {
            "current": 3381.414,
            "min": 1500.0,
            "max": 2250.0
        },
        {
            "current": 3391.557,
            "min": 1500.0,
            "max": 2250.0
        },
        {
            "current": 3405.05,
            "min": 1500.0,
            "max": 2250.0
        },
        {
            "current": 3383.606,
            "min": 1500.0,
            "max": 2250.0
        },
        {
            "current": 3383.409,
            "min": 1500.0,
            "max": 2250.0
        },
        {
            "current": 3385.499,
            "min": 1500.0,
            "max": 2250.0
        },
        {
            "current": 3403.744,
            "min": 1500.0,
            "max": 2250.0
        },
        {
            "current": 3395.92,
            "min": 1500.0,
            "max": 2250.0
        },
        {
            "current": 3391.424,
            "min": 1500.0,
            "max": 2250.0
        },
        {
            "current": 3391.769,
            "min": 1500.0,
            "max": 2250.0
        },
        {
            "current": 3385.303,
            "min": 1500.0,
            "max": 2250.0
        },
        {
            "current": 3385.049,
            "min": 1500.0,
            "max": 2250.0
        },
        {
            "current": 3377.755,
            "min": 1500.0,
            "max": 2250.0
        },
        {
            "current": 3383.927,
            "min": 1500.0,
            "max": 2250.0
        },
        {
            "current": 3397.06,
            "min": 1500.0,
            "max": 2250.0
        },
        {
            "current": 3403.768,
            "min": 1500.0,
            "max": 2250.0
        },
        {
            "current": 3393.898,
            "min": 1500.0,
            "max": 2250.0
        },
        {
            "current": 3387.652,
            "min": 1500.0,
            "max": 2250.0
        },
        {
            "current": 3368.872,
            "min": 1500.0,
            "max": 2250.0
        },
        {
            "current": 3388.523,
            "min": 1500.0,
            "max": 2250.0
        },
        {
            "current": 3385.918,
            "min": 1500.0,
            "max": 2250.0
        },
        {
            "current": 3370.688,
            "min": 1500.0,
            "max": 2250.0
        },
        {
            "current": 3388.257,
            "min": 1500.0,
            "max": 2250.0
        },
        {
            "current": 3387.274,
            "min": 1500.0,
            "max": 2250.0
        },
        {
            "current": 3380.864,
            "min": 1500.0,
            "max": 2250.0
        },
        {
            "current": 3392.187,
            "min": 1500.0,
            "max": 2250.0
        },
        {
            "current": 3389.307,
            "min": 1500.0,
            "max": 2250.0
        },
        {
            "current": 3392.774,
            "min": 1500.0,
            "max": 2250.0
        },
        {
            "current": 3389.115,
            "min": 1500.0,
            "max": 2250.0
        },
        {
            "current": 2345.919,
            "min": 1500.0,
            "max": 2250.0
        },
        {
            "current": 2422.135,
            "min": 1500.0,
            "max": 2250.0
        },
        {
            "current": 2352.941,
            "min": 1500.0,
            "max": 2250.0
        },
        {
            "current": 3391.849,
            "min": 1500.0,
            "max": 2250.0
        },
        {
            "current": 2463.319,
            "min": 1500.0,
            "max": 2250.0
        },
        {
            "current": 2225.946,
            "min": 1500.0,
            "max": 2250.0
        },
        {
            "current": 2511.184,
            "min": 1500.0,
            "max": 2250.0
        },
        {
            "current": 2458.034,
            "min": 1500.0,
            "max": 2250.0
        },
        {
            "current": 3390.411,
            "min": 1500.0,
            "max": 2250.0
        },
        {
            "current": 1694.502,
            "min": 1500.0,
            "max": 2250.0
        },
        {
            "current": 1694.232,
            "min": 1500.0,
            "max": 2250.0
        },
        {
            "current": 1696.084,
            "min": 1500.0,
            "max": 2250.0
        },
        {
            "current": 2388.281,
            "min": 1500.0,
            "max": 2250.0
        },
        {
            "current": 3392.322,
            "min": 1500.0,
            "max": 2250.0
        },
        {
            "current": 3393.242,
            "min": 1500.0,
            "max": 2250.0
        },
        {
            "current": 1893.282,
            "min": 1500.0,
            "max": 2250.0
        },
        {
            "current": 2430.563,
            "min": 1500.0,
            "max": 2250.0
        },
        {
            "current": 2471.567,
            "min": 1500.0,
            "max": 2250.0
        },
        {
            "current": 2408.033,
            "min": 1500.0,
            "max": 2250.0
        },
        {
            "current": 3392.27,
            "min": 1500.0,
            "max": 2250.0
        },
        {
            "current": 3149.915,
            "min": 1500.0,
            "max": 2250.0
        },
        {
            "current": 2528.408,
            "min": 1500.0,
            "max": 2250.0
        },
        {
            "current": 2516.556,
            "min": 1500.0,
            "max": 2250.0
        },
        {
            "current": 2508.503,
            "min": 1500.0,
            "max": 2250.0
        },
        {
            "current": 2505.504,
            "min": 1500.0,
            "max": 2250.0
        },
        {
            "current": 2545.606,
            "min": 1500.0,
            "max": 2250.0
        },
        {
            "current": 2474.186,
            "min": 1500.0,
            "max": 2250.0
        },
        {
            "current": 2514.34,
            "min": 1500.0,
            "max": 2250.0
        },
        {
            "current": 3394.877,
            "min": 1500.0,
            "max": 2250.0
        },
        {
            "current": 3389.7,
            "min": 1500.0,
            "max": 2250.0
        },
        {
            "current": 2498.582,
            "min": 1500.0,
            "max": 2250.0
        },
        {
            "current": 3384.11,
            "min": 1500.0,
            "max": 2250.0
        },
        {
            "current": 3391.32,
            "min": 1500.0,
            "max": 2250.0
        },
        {
            "current": 3392.812,
            "min": 1500.0,
            "max": 2250.0
        },
        {
            "current": 2346.684,
            "min": 1500.0,
            "max": 2250.0
        },
        {
            "current": 3390.138,
            "min": 1500.0,
            "max": 2250.0
        },
        {
            "current": 2440.805,
            "min": 1500.0,
            "max": 2250.0
        },
        {
            "current": 3393.741,
            "min": 1500.0,
            "max": 2250.0
        },
        {
            "current": 2367.428,
            "min": 1500.0,
            "max": 2250.0
        },
        {
            "current": 3389.861,
            "min": 1500.0,
            "max": 2250.0
        },
        {
            "current": 2830.613,
            "min": 1500.0,
            "max": 2250.0
        },
        {
            "current": 3400.137,
            "min": 1500.0,
            "max": 2250.0
        },
        {
            "current": 2467.782,
            "min": 1500.0,
            "max": 2250.0
        },
        {
            "current": 2363.042,
            "min": 1500.0,
            "max": 2250.0
        },
        {
            "current": 3395.551,
            "min": 1500.0,
            "max": 2250.0
        },
        {
            "current": 3383.066,
            "min": 1500.0,
            "max": 2250.0
        },
        {
            "current": 3398.046,
            "min": 1500.0,
            "max": 2250.0
        },
        {
            "current": 3389.797,
            "min": 1500.0,
            "max": 2250.0
        }
    ],
    "disk": {
        "total": 1757.8287315368652,
        "used": 600.7976264953613
    },
    "gpu": "A100-SXM4-40GB",
    "gpu_count": 4,
    "gpu_devices": [
        {
            "name": "A100-SXM4-40GB",
            "memory_total": 42506321920
        },
        {
            "name": "A100-SXM4-40GB",
            "memory_total": 42506321920
        },
        {
            "name": "A100-SXM4-40GB",
            "memory_total": 42506321920
        },
        {
            "name": "A100-SXM4-40GB",
            "memory_total": 42506321920
        }
    ],
    "memory": {
        "total": 1007.709156036377
    }
}
